{"id": {"govtrack": 412531, "bioguide": "C001093", "thomas": "02121", "cspan": 79719, "votesmart": 67851, "wikipedia": "Doug Collins (politician)", "fec": ["H2GA09150"], "opensecrets": "N00033518", "ballotpedia": "Doug Collins", "maplight": 1755, "icpsr": 21323, "wikidata": "Q3162841", "google_entity_id": "kg:/m/0lq9rkz"}, "name": {"first": "Doug", "last": "Collins", "official_full": "Doug Collins"}, "bio": {"gender": "M", "birthday": "1966-08-16"}, "terms": [{"type": "rep", "start": "2013-01-03", "end": "2015-01-03", "state": "GA", "party": "Republican", "district": 9, "office": "513 Cannon House Office Building", "address": "513 Cannon HOB; Washington DC 20515-1009", "phone": "202-225-9893", "url": "http://dougcollins.house.gov", "rss_url": "http://dougcollins.house.gov/latest-rss/latest-rss/", "contact_form": "https://dougcollins.house.gov/email-me", "fax": "202-226-1224"}, {"type": "rep", "start": "2015-01-06", "end": "2017-01-03", "state": "GA", "party": "Republican", "district": 9, "office": "1504 Longworth House Office Building", "address": "1504 Longworth HOB; Washington DC 20515-1009", "phone": "202-225-9893", "url": "http://dougcollins.house.gov", "rss_url": "http://dougcollins.house.gov/latest-rss/latest-rss/", "contact_form": "https://dougcollins.house.gov/email-me", "fax": "202-226-1224"}, {"type": "rep", "start": "2017-01-03", "end": "2019-01-03", "state": "GA", "district": 9, "party": "Republican", "phone": "202-225-9893", "url": "https://dougcollins.house.gov", "rss_url": "http://dougcollins.house.gov/latest-rss/latest-rss/", "address": "1504 Longworth HOB; Washington DC 20515-1009", "office": "1504 Longworth House Office Building", "fax": "202-226-1224"}], "photo_url": "/data/photos/C001093.jpg"}