{"id": {"bioguide": "D000612", "thomas": "01995", "govtrack": 412403, "opensecrets": "N00031593", "votesmart": 28769, "fec": ["H0CA19173"], "cspan": 623287, "wikipedia": "Jeff Denham", "house_history": 12597, "maplight": 1276, "icpsr": 21109, "wikidata": "Q1686295", "google_entity_id": "kg:/m/02q4gng"}, "name": {"first": "Jeff", "last": "Denham", "official_full": "Jeff Denham"}, "bio": {"birthday": "1967-07-29", "gender": "M"}, "terms": [{"type": "rep", "start": "2011-01-05", "end": "2013-01-03", "state": "CA", "district": 19, "party": "Republican", "url": "http://denham.house.gov/", "address": "1605 Longworth HOB; Washington DC 20515-0519", "phone": "202-225-4540", "fax": "202-225-3402", "office": "1605 Longworth House Office Building"}, {"type": "rep", "start": "2013-01-03", "end": "2015-01-03", "state": "CA", "party": "Republican", "district": 10, "url": "http://denham.house.gov", "address": "1730 Longworth HOB; Washington DC 20515-0510", "phone": "202-225-4540", "fax": "202-225-3402", "office": "1730 Longworth House Office Building", "rss_url": "http://denham.house.gov/rss.xml", "contact_form": "https://denham.house.gov/contact-me/email-me"}, {"type": "rep", "start": "2015-01-06", "end": "2017-01-03", "state": "CA", "party": "Republican", "district": 10, "url": "http://denham.house.gov", "address": "1730 Longworth HOB; Washington DC 20515-0510", "phone": "202-225-4540", "fax": "202-225-3402", "office": "1730 Longworth House Office Building", "rss_url": "http://denham.house.gov/rss.xml", "contact_form": "https://denham.house.gov/contact-me/email-me"}, {"type": "rep", "start": "2017-01-03", "end": "2019-01-03", "state": "CA", "district": 10, "party": "Republican", "phone": "202-225-4540", "url": "https://denham.house.gov", "rss_url": "http://denham.house.gov/rss.xml", "address": "1730 Longworth HOB; Washington DC 20515-0510", "office": "1730 Longworth House Office Building", "fax": "202-225-3402"}], "photo_url": "/data/photos/D000612.jpg"}