{"id": {"bioguide": "E000179", "thomas": "00344", "govtrack": 400122, "opensecrets": "N00001003", "votesmart": 26972, "icpsr": 15603, "fec": ["H8NY19058"], "cspan": 6109, "wikipedia": "Eliot Engel", "house_history": 12815, "maplight": 233, "wikidata": "Q1329618", "google_entity_id": "kg:/m/03tt1r"}, "name": {"first": "Eliot", "middle": "L.", "last": "Engel", "official_full": "Eliot L. Engel"}, "bio": {"birthday": "1947-02-18", "gender": "M", "religion": "Jewish"}, "terms": [{"type": "rep", "start": "1989-01-03", "end": "1991-01-03", "state": "NY", "district": 19, "party": "Democrat"}, {"type": "rep", "start": "1991-01-03", "end": "1993-01-03", "state": "NY", "district": 19, "party": "Democrat"}, {"type": "rep", "start": "1993-01-05", "end": "1995-01-03", "state": "NY", "district": 17, "party": "Democrat"}, {"type": "rep", "start": "1995-01-04", "end": "1997-01-03", "state": "NY", "district": 17, "party": "Democrat"}, {"type": "rep", "start": "1997-01-07", "end": "1999-01-03", "state": "NY", "district": 17, "party": "Democrat"}, {"type": "rep", "start": "1999-01-06", "end": "2001-01-03", "state": "NY", "district": 17, "party": "Democrat"}, {"type": "rep", "start": "2001-01-03", "end": "2003-01-03", "state": "NY", "district": 17, "party": "Democrat"}, {"type": "rep", "start": "2003-01-07", "end": "2005-01-03", "state": "NY", "district": 17, "party": "Democrat", "url": "http://www.house.gov/engel"}, {"type": "rep", "start": "2005-01-04", "end": "2007-01-03", "state": "NY", "district": 17, "party": "Democrat", "url": "http://www.house.gov/engel"}, {"type": "rep", "start": "2007-01-04", "end": "2009-01-03", "state": "NY", "district": 17, "party": "Democrat", "url": "http://www.house.gov/engel"}, {"type": "rep", "start": "2009-01-06", "end": "2011-01-03", "state": "NY", "district": 17, "party": "Democrat", "url": "http://www.house.gov/engel"}, {"type": "rep", "start": "2011-01-05", "end": "2013-01-03", "state": "NY", "district": 17, "party": "Democrat", "url": "http://www.house.gov/engel", "address": "2161 Rayburn HOB; Washington DC 20515-3217", "phone": "202-225-2464", "fax": "202-225-5513", "contact_form": "http://www.house.gov/writerep", "office": "2161 Rayburn House Office Building"}, {"type": "rep", "start": "2013-01-03", "end": "2015-01-03", "state": "NY", "party": "Democrat", "district": 16, "url": "http://engel.house.gov", "address": "2161 Rayburn HOB; Washington DC 20515-3216", "phone": "202-225-2464", "fax": "202-225-5513", "contact_form": "https://engel.house.gov/write-your-rep1", "office": "2161 Rayburn House Office Building"}, {"type": "rep", "start": "2015-01-06", "end": "2017-01-03", "state": "NY", "party": "Democrat", "district": 16, "url": "http://engel.house.gov", "address": "2462 Rayburn HOB; Washington DC 20515-3216", "phone": "202-225-2464", "fax": "202-225-5513", "contact_form": "https://engel.house.gov/write-your-rep1", "office": "2462 Rayburn House Office Building"}, {"type": "rep", "start": "2017-01-03", "end": "2019-01-03", "state": "NY", "district": 16, "party": "Democrat", "phone": "202-225-2464", "url": "https://engel.house.gov", "address": "2462 Rayburn HOB; Washington DC 20515-3216", "office": "2462 Rayburn House Office Building", "fax": "202-225-5513"}], "photo_url": "/data/photos/E000179.jpg"}