{"id": {"bioguide": "E000298", "fec": ["H8KS04112"], "govtrack": 412735, "wikipedia": "Ron Estes", "wikidata": "Q7363747", "ballotpedia": "Ron Estes", "votesmart": 125031, "house_history": 15032448694, "cspan": 107963, "maplight": 2246, "google_entity_id": "kg:/m/0gfgsrm", "opensecrets": "N00040712"}, "name": {"first": "Ron", "last": "Estes", "official_full": "Ron Estes"}, "bio": {"birthday": "1956-07-19", "gender": "M"}, "terms": [{"type": "rep", "start": "2017-04-25", "end": "2019-01-03", "state": "KS", "district": 4, "party": "Republican", "url": "https://estes.house.gov", "contact_form": "https://estes.house.gov/contact/email", "address": "2452 Rayburn HOB; Washington DC 20515-1604", "office": "2452 Rayburn House Office Building", "phone": "202-225-6216"}], "photo_url": null}