{"id": {"bioguide": "P000610", "fec": ["H2VI00082"], "govtrack": 412659, "opensecrets": "N00035000", "thomas": "02274", "house_history": 15032410230, "maplight": 2115, "wikidata": "Q18739104", "wikipedia": "Stacey Plaskett", "google_entity_id": "kg:/m/012844_c", "cspan": 79090}, "name": {"first": "Stacey", "last": "Plaskett", "official_full": "Stacey E. Plaskett"}, "bio": {"gender": "F", "birthday": "1964-05-13"}, "terms": [{"type": "rep", "start": "2015-01-06", "end": "2017-01-03", "state": "VI", "district": 0, "party": "Democrat", "address": "509 Cannon HOB; Washington DC 20515-5500", "office": "509 Cannon House Office Building", "phone": "202-225-1790", "url": "https://plaskett.house.gov", "fax": "202-225-5517"}, {"type": "rep", "start": "2017-01-03", "end": "2019-01-03", "state": "VI", "district": 0, "party": "Democrat", "phone": "202-225-1790", "url": "https://plaskett.house.gov", "address": "331 Cannon HOB; Washington DC 20515-5500", "office": "331 Cannon House Office Building", "fax": "202-225-5517"}], "photo_url": "/data/photos/P000610.jpg"}