{"id": {"bioguide": "Z000017", "fec": ["H8NY01148"], "govtrack": 412646, "opensecrets": "N00029404", "thomas": "02261", "maplight": 2102, "wikidata": "Q16221257", "wikipedia": "Lee Zeldin", "google_entity_id": "kg:/m/03h4jcq", "cspan": 61616, "icpsr": 21539, "votesmart": 110252}, "name": {"first": "Lee", "last": "Zeldin", "official_full": "Lee M. Zeldin"}, "bio": {"gender": "M", "birthday": "1980-01-30"}, "terms": [{"type": "rep", "start": "2015-01-06", "end": "2017-01-03", "state": "NY", "district": 1, "party": "Republican", "address": "1517 Longworth HOB; Washington DC 20515-3201", "office": "1517 Longworth House Office Building", "phone": "202-225-3826", "url": "https://zeldin.house.gov", "fax": "202-225-3143"}, {"type": "rep", "start": "2017-01-03", "end": "2019-01-03", "state": "NY", "district": 1, "party": "Republican", "phone": "202-225-3826", "url": "https://zeldin.house.gov", "address": "1517 Longworth HOB; Washington DC 20515-3201", "office": "1517 Longworth House Office Building", "fax": "202-225-3143"}], "photo_url": "/data/photos/Z000017.jpg"}